{"id":22294,"title":"Centrifuge the whole blood to separate red blood cells","title_html":"Centrifuge the whole blood to separate red blood cells","image":{"source":"https:\/\/www.protocols.io\/img\/default_protocol.png","placeholder":"https:\/\/www.protocols.io\/img\/default_protocol.png"},"doi":"dx.doi.org\/10.17504\/protocols.io.zzwf77e","doi_status":2,"uri":"centrifuge-the-whole-blood-to-separate-red-blood-c-zzwf77e","type_id":1,"published_on":1555357394,"version_id":0,"created_on":1555017770,"categories":null,"creator":{"name":"George Lykotrafitis","affiliation":null,"username":"george-lykotrafitis","link":null,"image":{"source":"\/img\/avatars\/006.png","placeholder":"\/img\/avatars\/006.png"},"badges":[{"id":2,"image":{"source":"\/img\/badges\/bronze.svg","placeholder":"\/img\/badges\/bronze.svg"},"name":"Author"}],"research_interests":null},"journal":null,"journal_name":null,"journal_link":null,"public":1,"has_versions":0,"link":null,"total_collections":0,"number_of_steps":9,"authors":[{"name":"George Lykotrafitis","affiliation":"University of Connecticut","username":"george-lykotrafitis","link":null,"image":{"source":"\/img\/avatars\/006.png","placeholder":"\/img\/avatars\/006.png"},"badges":[],"research_interests":null}],"versions":[],"groups":[],"has_subprotocols":0,"is_subprotocol":0,"is_bookmarked":0,"forks_count":{"private":0,"public":0},"access":{"can_view":1,"can_remove":0,"can_add":0,"can_edit":0,"can_publish":0,"can_get_doi":0,"can_share":1,"can_move":1,"can_move_outside":1,"can_transfer":1,"can_download":1,"is_locked":0},"steps":[{"id":730319,"guid":"AAC233005C9F11E9A7501F09D2A5B01D","previous_id":null,"previous_guid":null,"modified_on":0,"protocol_id":0,"components":[{"id":1054723,"guid":"BAC3C826BE1A41EBAB02FECA18316772","order_id":1,"type_id":6,"title":"Section","source":{"title":""}},{"id":1054724,"guid":"8CED725B54F64DE286D828B5BD7221AA","order_id":1,"type_id":1,"title":"description","source":{"description":"<div class = \"text-blocks\"><div class = \"text-block\">Centrifuge the whole blood using the parameters: 500 \u00d7g,  4 \u2103, and 5 min.<\/div><\/div>"}}],"cases":null,"data":null,"section":null,"section_color":null},{"id":730320,"guid":"5A2DBB205CA011E9A7501F09D2A5B01D","previous_id":730319,"previous_guid":"AAC233005C9F11E9A7501F09D2A5B01D","modified_on":0,"protocol_id":0,"components":[{"id":1054723,"guid":"866302F937294EF79173039BF0F220ED","order_id":1,"type_id":6,"title":"Section","source":{"title":""}},{"id":1054724,"guid":"1DAF09C13AC44C578872D7ED1FA1F748","order_id":1,"type_id":1,"title":"description","source":{"description":"<div class = \"text-blocks\"><div class = \"text-block\">Remove the plasma and buffy coat.<\/div><\/div>"}}],"cases":null,"data":null,"section":null,"section_color":null},{"id":730321,"guid":"67A107805CA011E9A7501F09D2A5B01D","previous_id":730320,"previous_guid":"5A2DBB205CA011E9A7501F09D2A5B01D","modified_on":0,"protocol_id":0,"components":[{"id":1054723,"guid":"8C12967E4BEA448AB1E4752872DEE5D9","order_id":1,"type_id":6,"title":"Section","source":{"title":""}},{"id":1054724,"guid":"8AB404CDDDF941ABA218072E3C3D961C","order_id":1,"type_id":1,"title":"description","source":{"description":"<div class = \"text-blocks\"><div class = \"text-block\">Add the same volume of Alsever's solution as the remaining blood components.<\/div><\/div>"}}],"cases":null,"data":null,"section":null,"section_color":null},{"id":730322,"guid":"D45F9F305CA011E9A7501F09D2A5B01D","previous_id":730321,"previous_guid":"67A107805CA011E9A7501F09D2A5B01D","modified_on":0,"protocol_id":0,"components":[{"id":1054723,"guid":"C496F387BA4641658590BB8213D1F094","order_id":1,"type_id":6,"title":"Section","source":{"title":""}},{"id":1054724,"guid":"5DBE8A4680514CAA867267AD376D8921","order_id":1,"type_id":1,"title":"description","source":{"description":"<div class = \"text-blocks\"><div class = \"text-block\">Centrifuge again using the parameters: 500 \u00d7g,  4 \u2103, and 5 min.<\/div><\/div>"}}],"cases":null,"data":null,"section":null,"section_color":null},{"id":730323,"guid":"DDE70B605CA011E9A7501F09D2A5B01D","previous_id":730322,"previous_guid":"D45F9F305CA011E9A7501F09D2A5B01D","modified_on":0,"protocol_id":0,"components":[{"id":1054723,"guid":"1BA433716FED4B0CBD7E7DA32BFBA472","order_id":1,"type_id":6,"title":"Section","source":{"title":""}},{"id":1054724,"guid":"19A663D4D3534D9C974020EB27177D91","order_id":1,"type_id":1,"title":"description","source":{"description":"<div class = \"text-blocks\"><div class = \"text-block\">Remove the top layer.<\/div><\/div>"}}],"cases":null,"data":null,"section":null,"section_color":null},{"id":730324,"guid":"13B85B905CA111E9A7501F09D2A5B01D","previous_id":730323,"previous_guid":"DDE70B605CA011E9A7501F09D2A5B01D","modified_on":0,"protocol_id":0,"components":[{"id":1054723,"guid":"E79B7583C1F54780B9445A1109E16EB1","order_id":1,"type_id":6,"title":"Section","source":{"title":""}},{"id":1054724,"guid":"7BC735716EC043A3AD39F7723C6228EF","order_id":1,"type_id":1,"title":"description","source":{"description":"<div class = \"text-blocks\"><div class = \"text-block\">Add the same volume of Alsever's solution as the remaining blood components.<\/div><\/div>"}}],"cases":null,"data":null,"section":null,"section_color":null},{"id":730325,"guid":"1B9880605CA111E9A7501F09D2A5B01D","previous_id":730324,"previous_guid":"13B85B905CA111E9A7501F09D2A5B01D","modified_on":0,"protocol_id":0,"components":[{"id":1054723,"guid":"60A1BC64AE284122AF15917E561CE393","order_id":1,"type_id":6,"title":"Section","source":{"title":""}},{"id":1054724,"guid":"F3424936919F4A0C975DE1AC4DB9B634","order_id":1,"type_id":1,"title":"description","source":{"description":"<div class = \"text-blocks\"><div class = \"text-block\">Centrifuge a third time using the parameters: 500 \u00d7g,  4 \u2103, and 5 min.<\/div><\/div>"}}],"cases":null,"data":null,"section":null,"section_color":null},{"id":730326,"guid":"2FF0A1A05CA111E9A7501F09D2A5B01D","previous_id":730325,"previous_guid":"1B9880605CA111E9A7501F09D2A5B01D","modified_on":0,"protocol_id":0,"components":[{"id":1054723,"guid":"A28CDED562A54527B5D9EB18CF55DE43","order_id":1,"type_id":6,"title":"Section","source":{"title":""}},{"id":1054724,"guid":"01529C3DD46143348C824B86D35046D4","order_id":1,"type_id":1,"title":"description","source":{"description":"<div class = \"text-blocks\"><div class = \"text-block\">Remove the top layer.<\/div><\/div>"}}],"cases":null,"data":null,"section":null,"section_color":null},{"id":730327,"guid":"3DFE0B205CA111E9A7501F09D2A5B01D","previous_id":730326,"previous_guid":"2FF0A1A05CA111E9A7501F09D2A5B01D","modified_on":0,"protocol_id":0,"components":[{"id":1054723,"guid":"D74D482C895D4E6BA2BE1D921C58D0C9","order_id":1,"type_id":6,"title":"Section","source":{"title":""}},{"id":1054724,"guid":"F23F383ACA204E6AAFE2F6DC20B56069","order_id":1,"type_id":1,"title":"description","source":{"description":"<div class = \"text-blocks\"><div class = \"text-block\">Add the same volume of Alsever's solution as the remaining blood component - red blood cells, and store at 4 \u2103 for up to 7 days.<\/div><\/div>"}}],"cases":null,"data":null,"section":null,"section_color":null}],"materials":[],"description":"<div class = \"text-blocks\"><div class = \"text-block\">Centrifuge the whole blood in order to obtain the red blood cells.<\/div><\/div>","changed_on":1555357394}