{"uri":"lymphocyte-proliferation-in-poultry-species-s7kehkw","version_id":"0","protocol_name":"Lymphocyte proliferation in poultry species","protocol_name_html":"Lymphocyte proliferation in poultry species","is_prepublished":"0","can_edit":"0","parent_id":null,"api_version":"1","is_new_mode":"0","last_modified":"1535912405","type_id":"1","link":null,"fork_id":"","public_fork_note":"","number_of_steps":"11","has_versions":"0","first_published_date":"1535912328","publish_date":"2018-09-02 18:20:05","documents":null,"have_protocol_in_step":"0","is_protocol_in_step":"0","vendor_name":"Contributed by users","vendor_link":"https:\/\/www.protocols.io","vendor_logo":"\/img\/vendors\/1.png","mod_mins":"-26","mod_secs":"1","description":null,"is_bookmarked":"0","can_reassign":"1","before_start":null,"has_guidelines":"0","materials":[],"warning":null,"version_class":"15308","public":"1","is_owner":"1","is_original_owner":"1","created_on":"1535911684","protocol_affiliation":"Cairo University","affiliation":"Cairo University","doi":"dx.doi.org\/10.17504\/protocols.io.s7kehkw","doi_status":"1","changed_fork_steps":null,"profile_url":"GamalMehaisen-w2t25413y2w2","protocol_img":"https:\/\/www.protocols.io\/img\/default_protocol.png","profile_image":"https:\/\/s3.amazonaws.com\/pr-journal\/6p63cjw.jpg","full_name":"Gamal Mehaisen","created_by":"Gamal Mehaisen","private_link":"E0253B08F8E3D77C6FC23E5890C524F7","original_img":"1","username":"gamal-mehaisen","is_retracted":"0","retraction_reason":null,"plos_id":null,"manuscript_citation":"<p>Mehaisen GMK, Eshak MG, Elkaiaty AM,\u00a0Atta A-RMM, Mashaly MM, Abass AO (2017)\u00a0Comprehensive growth performance, immune\u00a0function, plasma biochemistry, gene expressions\u00a0and cell death morphology responses to a daily\u00a0corticosterone injection course in broiler chickens.\u00a0PLoS ONE 12(2): e0172684. doi:10.1371\/journal.pone.0172684\u00a0<\/p>","journal_name":null,"is_donations_disabled":"0","is_donations_disabled_by_user":"9","item_record_id":351100,"fork_info":[],"compare_forks":[],"protocols":[],"groups":[],"number_of_shared_runs":[],"ownership_history":[],"keywords":"","transfer_to_user":[],"sub_transfer":false,"is_transfer_pending":false,"number_of_bookmarks":"0","collections":[],"tags":[],"archived":0,"sub_authors":[],"sub_protocols_number":0,"can_edit_shared":0,"shared_runs":[],"is_shared_run":0,"is_shared":1,"banner":null,"contact_badges":[{"badge_id":"2","badge_image":"\/img\/badges\/bronze.svg","badge_description":"Author!"}],"number_of_comments":0,"is_locked":0,"is_locked_by":false,"authors":"Ahmed O.Abass,Gamal Mehaisen","authors_list":[{"name":"Ahmed O.Abass","affiliation":"Cairo University","username":null,"profile_image":null},{"name":"Gamal Mehaisen","affiliation":"Cairo University","username":"gamal-mehaisen","profile_image":"https:\/\/s3.amazonaws.com\/pr-journal\/6p63cjw.jpg"}],"user":{"profile_image":"https:\/\/s3.amazonaws.com\/pr-journal\/6p63cjw.jpg","username":"gamal-mehaisen","full_name":"Gamal Mehaisen","created_by":"Gamal Mehaisen"},"access":{"can_view":"1","can_remove":"0","can_add":"0","can_edit":0,"can_publish":0,"can_get_doi":0,"can_share":"0","can_move":"1","can_transfer":"1","can_download":"1","is_locked":"0"},"is_contact_suspended":0,"guidelines":null,"status_id":"1","is_research":"1","status_info":"We use this protocol in our group and it is working","steps":[{"id":"660338","is_changed":"0","original_id":"0","is_skipped":"0","is_checked":"0","guid":"BB3087586F274C47A2E6AE8C5C127FC0","previous_guid":null,"previous_id":"0","last_modified":"1535911824","components":[{"component_id":"1189672","previous_id":0,"original_id":"0","guid":"2A2B1443B34D4D699954E3EDB0BFD59D","previous_guid":null,"component_type_id":"1","data_id":null,"data":"The heparinized blood samples were added to separation medium Histopaque\u00ae-1077 (cat# 10771, Sigma, USA).","order_id":"0","name":"Description","data_by_id":"0","type_id":"1","source_data":{"description":"The heparinized blood samples were added to separation medium Histopaque\u00ae-1077 (cat# 10771, Sigma, USA)."},"is_project":0},{"component_id":"1189673","previous_id":"1189672","original_id":"0","guid":"7A2BA016A6214E09A73238BC028FFEB6","previous_guid":"2A2B1443B34D4D699954E3EDB0BFD59D","component_type_id":"6","data_id":"0","data":"","order_id":"1","name":"Section","data_by_id":"0","type_id":"6","source_data":{"section":""},"is_project":0}]},{"id":"660339","is_changed":"0","original_id":"0","is_skipped":"0","is_checked":"0","guid":"D9F326D35D2546B69C8600ED54EC8E6A","previous_guid":"BB3087586F274C47A2E6AE8C5C127FC0","previous_id":"660338","last_modified":"1535911824","components":[{"component_id":"1189674","previous_id":0,"original_id":"0","guid":"586562B413704CD982DB23637CDD527D","previous_guid":null,"component_type_id":"1","data_id":null,"data":"Samples were centrifuged at 1030 xg for 20 min at 4\u00b0C.","order_id":"0","name":"Description","data_by_id":"0","type_id":"1","source_data":{"description":"Samples were centrifuged at 1030 xg for 20 min at 4\u00b0C."},"is_project":0},{"component_id":"1189675","previous_id":"1189674","original_id":"0","guid":"7E258A1370A14683AE0E1024EA6D6F36","previous_guid":"586562B413704CD982DB23637CDD527D","component_type_id":"6","data_id":"0","data":"","order_id":"1","name":"Section","data_by_id":"0","type_id":"6","source_data":{"section":""},"is_project":0}]},{"id":"660340","is_changed":"0","original_id":"0","is_skipped":"0","is_checked":"0","guid":"57FCC17E23B44BA8964A9B5665336CE0","previous_guid":"D9F326D35D2546B69C8600ED54EC8E6A","previous_id":"660339","last_modified":"1535911824","components":[{"component_id":"1189676","previous_id":0,"original_id":"0","guid":"C068DAEDEDDA460F8005D5ECB6112944","previous_guid":null,"component_type_id":"1","data_id":null,"data":"Peripheral blood mononuclear cells (PBMCs) were isolated and washed twice with RPMI-1640 (Invitrogen Corp., Grand Island, NY, USA) and then re-suspended in 2 ml of RPMI-1640 complete culture medium.","order_id":"0","name":"Description","data_by_id":"0","type_id":"1","source_data":{"description":"Peripheral blood mononuclear cells (PBMCs) were isolated and washed twice with RPMI-1640 (Invitrogen Corp., Grand Island, NY, USA) and then re-suspended in 2 ml of RPMI-1640 complete culture medium."},"is_project":0},{"component_id":"1189677","previous_id":"1189676","original_id":"0","guid":"277BE7E6C4A94DFD987199CC7C44D14A","previous_guid":"C068DAEDEDDA460F8005D5ECB6112944","component_type_id":"6","data_id":"0","data":"","order_id":"1","name":"Section","data_by_id":"0","type_id":"6","source_data":{"section":""},"is_project":0}]},{"id":"660341","is_changed":"0","original_id":"0","is_skipped":"0","is_checked":"0","guid":"7842C541CE4746BFBCF4D374E22148F8","previous_guid":"57FCC17E23B44BA8964A9B5665336CE0","previous_id":"660340","last_modified":"1535912099","components":[{"component_id":"1189679","previous_id":0,"original_id":"0","guid":"E6A51C4A624E474BAD92D594FB68C85B","previous_guid":null,"component_type_id":"6","data_id":"0","data":"","order_id":"0","name":"Section","data_by_id":"0","type_id":"6","source_data":{"section":""},"is_project":0},{"component_id":"1189678","previous_id":"1189679","original_id":"0","guid":"494339B716CE4B14A5EC0ADF52F0EFF8","previous_guid":"E6A51C4A624E474BAD92D594FB68C85B","component_type_id":"1","data_id":null,"data":"<p>The viable lymphocytes were detected using Trypan Blue dye and plated in triplicate wells (96-well plate) at 1\u00d710<sup>6<\/sup> cells per well.<\/p>","order_id":"1","name":"Description","data_by_id":"0","type_id":"1","source_data":{"description":"<p>The viable lymphocytes were detected using Trypan Blue dye and plated in triplicate wells (96-well plate) at 1\u00d710<sup>6<\/sup> cells per well.<\/p>"},"is_project":0}]},{"id":"660342","is_changed":"0","original_id":"0","is_skipped":"0","is_checked":"0","guid":"68DD715E1DE6482D8AE4AB3ED9488892","previous_guid":"7842C541CE4746BFBCF4D374E22148F8","previous_id":"660341","last_modified":"1535911824","components":[{"component_id":"1189680","previous_id":0,"original_id":"0","guid":"A1DE14270B0B430BBCACCEC317351F3E","previous_guid":null,"component_type_id":"1","data_id":null,"data":"A 50 \u03bcl of either Concanavalin-A (Con-A, 45 \u03bcg\/ml, cat# C5275, Sigma, USA) or Lipopolysaccharide (LPS, 10 \u03bcg\/ml, cat# L4391, Sigma, USA) was added to selected wells to induce the proliferation of T lymphocyte and B lymphocyte, respectively.","order_id":"0","name":"Description","data_by_id":"0","type_id":"1","source_data":{"description":"A 50 \u03bcl of either Concanavalin-A (Con-A, 45 \u03bcg\/ml, cat# C5275, Sigma, USA) or Lipopolysaccharide (LPS, 10 \u03bcg\/ml, cat# L4391, Sigma, USA) was added to selected wells to induce the proliferation of T lymphocyte and B lymphocyte, respectively."},"is_project":0},{"component_id":"1189681","previous_id":"1189680","original_id":"0","guid":"D488DD3D7A5F4172B6937DBB62B3D2F3","previous_guid":"A1DE14270B0B430BBCACCEC317351F3E","component_type_id":"6","data_id":"0","data":"","order_id":"1","name":"Section","data_by_id":"0","type_id":"6","source_data":{"section":""},"is_project":0}]},{"id":"660343","is_changed":"0","original_id":"0","is_skipped":"0","is_checked":"0","guid":"4B102DD869BB438EB04756B2A320568F","previous_guid":"68DD715E1DE6482D8AE4AB3ED9488892","previous_id":"660342","last_modified":"1535911824","components":[{"component_id":"1189682","previous_id":0,"original_id":"0","guid":"AD434754CFF64C5588000A1030276EEB","previous_guid":null,"component_type_id":"1","data_id":null,"data":"Control wells received 50 \u03bcl of RPMI-1640 medium.","order_id":"0","name":"Description","data_by_id":"0","type_id":"1","source_data":{"description":"Control wells received 50 \u03bcl of RPMI-1640 medium."},"is_project":0},{"component_id":"1189683","previous_id":"1189682","original_id":"0","guid":"FEBC07CF312C4ED1AAE5844C1E4CC9CB","previous_guid":"AD434754CFF64C5588000A1030276EEB","component_type_id":"6","data_id":"0","data":"","order_id":"1","name":"Section","data_by_id":"0","type_id":"6","source_data":{"section":""},"is_project":0}]},{"id":"660344","is_changed":"0","original_id":"0","is_skipped":"0","is_checked":"0","guid":"1F9F9AB07B344AA08934A56595BCA5B0","previous_guid":"4B102DD869BB438EB04756B2A320568F","previous_id":"660343","last_modified":"1535912133","components":[{"component_id":"1189685","previous_id":0,"original_id":"0","guid":"200171A9A8904D1F8D70475EE885B6E4","previous_guid":null,"component_type_id":"6","data_id":"0","data":"","order_id":"0","name":"Section","data_by_id":"0","type_id":"6","source_data":{"section":""},"is_project":0},{"component_id":"1189684","previous_id":"1189685","original_id":"0","guid":"768981DA439B45868FEAC5C8F6029F66","previous_guid":"200171A9A8904D1F8D70475EE885B6E4","component_type_id":"1","data_id":null,"data":"<p>Cells were then incubated for 48 h at 42 \u00b0C with 5 % CO<sub>2<\/sub>.<\/p>","order_id":"1","name":"Description","data_by_id":"0","type_id":"1","source_data":{"description":"<p>Cells were then incubated for 48 h at 42 \u00b0C with 5 % CO<sub>2<\/sub>.<\/p>"},"is_project":0}]},{"id":"660345","is_changed":"0","original_id":"0","is_skipped":"0","is_checked":"0","guid":"BFEC06837E784BC4BC812FA5FF5319C5","previous_guid":"1F9F9AB07B344AA08934A56595BCA5B0","previous_id":"660344","last_modified":"1535911824","components":[{"component_id":"1189686","previous_id":0,"original_id":"0","guid":"6C7AEC731E6248B883E45F15953476D5","previous_guid":null,"component_type_id":"1","data_id":null,"data":"After incubation, 15 \u03bcl of 3-[4,5-dimethylthiazol]-2,5-diphenyltetrazolium bromide (MTT, 5 mg\/ml, cat# M2128 , Sigma, USA) was added to each well and the cells were incubated for another 4 h.","order_id":"0","name":"Description","data_by_id":"0","type_id":"1","source_data":{"description":"After incubation, 15 \u03bcl of 3-[4,5-dimethylthiazol]-2,5-diphenyltetrazolium bromide (MTT, 5 mg\/ml, cat# M2128 , Sigma, USA) was added to each well and the cells were incubated for another 4 h."},"is_project":0},{"component_id":"1189687","previous_id":"1189686","original_id":"0","guid":"92C1058DECA64C64AB99997FDC19A7F5","previous_guid":"6C7AEC731E6248B883E45F15953476D5","component_type_id":"6","data_id":"0","data":"","order_id":"1","name":"Section","data_by_id":"0","type_id":"6","source_data":{"section":""},"is_project":0}]},{"id":"660346","is_changed":"0","original_id":"0","is_skipped":"0","is_checked":"0","guid":"C89FC00EB8C9405B91FACDEAF1ADCCF3","previous_guid":"BFEC06837E784BC4BC812FA5FF5319C5","previous_id":"660345","last_modified":"1535911824","components":[{"component_id":"1189688","previous_id":0,"original_id":"0","guid":"B529F8319FC045E1BAF997DA068F0A8D","previous_guid":null,"component_type_id":"1","data_id":null,"data":"Subsequently, 100 \u03bcl of 10% sodium dodecyl sulfate dissolved in 0.04 M HCl solution was added to each well to lyse the cells and solubilize the MTT crystals.","order_id":"0","name":"Description","data_by_id":"0","type_id":"1","source_data":{"description":"Subsequently, 100 \u03bcl of 10% sodium dodecyl sulfate dissolved in 0.04 M HCl solution was added to each well to lyse the cells and solubilize the MTT crystals."},"is_project":0},{"component_id":"1189689","previous_id":"1189688","original_id":"0","guid":"3FF78AC006D44C298227D6118F464B4C","previous_guid":"B529F8319FC045E1BAF997DA068F0A8D","component_type_id":"6","data_id":"0","data":"","order_id":"1","name":"Section","data_by_id":"0","type_id":"6","source_data":{"section":""},"is_project":0}]},{"id":"660347","is_changed":"0","original_id":"0","is_skipped":"0","is_checked":"0","guid":"B741AC7C27224EC68E24A79E928CF3D2","previous_guid":"C89FC00EB8C9405B91FACDEAF1ADCCF3","previous_id":"660346","last_modified":"1535911827","components":[{"component_id":"1189690","previous_id":0,"original_id":"0","guid":"951061833AE7450C9AE06636923B0E10","previous_guid":null,"component_type_id":"1","data_id":null,"data":"Finally, the absorbance at 570 nm was recorded using an automated ELISA microplate reader (ChroMate\u00ae Microplate Reader-4300, Awareness Technology Inc., Palm City, FL, USA).","order_id":"0","name":"Description","data_by_id":"0","type_id":"1","source_data":{"description":"Finally, the absorbance at 570 nm was recorded using an automated ELISA microplate reader (ChroMate\u00ae Microplate Reader-4300, Awareness Technology Inc., Palm City, FL, USA)."},"is_project":0},{"component_id":"1189691","previous_id":"1189690","original_id":"0","guid":"F650974B01A84B7891FBAE9CC5C4165D","previous_guid":"951061833AE7450C9AE06636923B0E10","component_type_id":"6","data_id":"0","data":"","order_id":"1","name":"Section","data_by_id":"0","type_id":"6","source_data":{"section":""},"is_project":0}]},{"id":"660348","is_changed":"0","original_id":"0","is_skipped":"0","is_checked":"0","guid":"DC5BB90AA4F94030840117CD50AE2989","previous_guid":"B741AC7C27224EC68E24A79E928CF3D2","previous_id":"660347","last_modified":"1535912175","components":[{"component_id":"1189693","previous_id":0,"original_id":"0","guid":"29F4D9CAF1D84A2B94C4FB23716AAFD7","previous_guid":null,"component_type_id":"6","data_id":"0","data":"","order_id":"0","name":"Section","data_by_id":"0","type_id":"6","source_data":{"section":""},"is_project":0},{"component_id":"1189692","previous_id":"1189693","original_id":"0","guid":"AC14DEFD9C914DC099C1F88857990CBC","previous_guid":"29F4D9CAF1D84A2B94C4FB23716AAFD7","component_type_id":"1","data_id":null,"data":"<p>Stimulating index (SI) for either T or B cells was calculated as follows: SI = OD570 <sub>(stimulated cells)<\/sub> \/ OD570 <sub>(unstimulated cells)<\/sub>.<\/p>","order_id":"1","name":"Description","data_by_id":"0","type_id":"1","source_data":{"description":"<p>Stimulating index (SI) for either T or B cells was calculated as follows: SI = OD570 <sub>(stimulated cells)<\/sub> \/ OD570 <sub>(unstimulated cells)<\/sub>.<\/p>"},"is_project":0}]}]}